pydotenvs/__init__.py
pydotenvs/cli.py
pydotenvs/main.py
pydotenvs/version.py
pydotenvs-0.2.0.dist-info/LICENSE
pydotenvs-0.2.0.dist-info/METADATA
pydotenvs-0.2.0.dist-info/WHEEL
pydotenvs-0.2.0.dist-info/entry_points.txt
pydotenvs-0.2.0.dist-info/top_level.txt
pydotenvs-0.2.0.dist-info/RECORD
