Metadata-Version: 2.1
Name: pydotenvs
Version: 0.2.0
Summary: Import environment variables from your .env file or run as command line tool; PyDotEnv Cli.
Home-page: https://github.com/ableinc/pyenv
Author: Jaylen Douglas
Author-email: douglas.jaylen@gmail.com
Keywords: environment variables,deployments,settings,env,pydotenvs,configurations,python,pydotenvs,python3,dependencies
Classifier: Programming Language :: Python :: 2
Classifier: Programming Language :: Python :: 3
Classifier: License :: OSI Approved :: MIT License
Classifier: Operating System :: OS Independent
License-File: LICENSE
